robomentor_client/__config__.py
robomentor_client/__init__.py
robomentor_client/framework/__init__.py
robomentor_client/framework/device/__init__.py
robomentor_client/framework/device/camera.py
robomentor_client/framework/device/gpio.py
robomentor_client/framework/device/serial.py
robomentor_client/framework/log/__init__.py
robomentor_client/framework/log/log.py
robomentor_client/framework/platform/__init__.py
robomentor_client/framework/platform/ep.py
robomentor_client/framework/platform/servo_robot.py
robomentor_client/framework/service/__init__.py
robomentor_client/framework/service/ai.py
robomentor_client/framework/service/message.py
robomentor_client/framework/service/requests.py
robomentor_client/framework/service/socket.py
robomentor_client/framework/service/system.py
RoboMentor_Client-2.9.4.dist-info/METADATA
RoboMentor_Client-2.9.4.dist-info/WHEEL
RoboMentor_Client-2.9.4.dist-info/top_level.txt
RoboMentor_Client-2.9.4.dist-info/RECORD
