Metadata-Version: 2.1
Name: RoboMentor-Client
Version: 2.9.4
Summary: Python library and framework for robomentor_client.
Home-page: https://github.com/robomentor/RoboMentor_Client
Author: Super Yang
Author-email: admin@wileho.com
License: MIT
Platform: UNKNOWN
Classifier: License :: OSI Approved :: MIT License
Classifier: Programming Language :: Python :: 3
Classifier: Programming Language :: Python :: 3.6
Classifier: Programming Language :: Python :: 3.7
Classifier: Programming Language :: Python :: Implementation :: CPython
Classifier: Programming Language :: Python :: Implementation :: PyPy
Requires-Python: >=3.6.0
Requires-Dist: paho-mqtt
Requires-Dist: psutil
Requires-Dist: rpi.gpio
Provides-Extra: python_3.6.x_needs
Requires-Dist: dataclasses ; extra == 'python_3.6.x_needs'
